snaphu-0.4.1.dist-info/RECORD
snaphu-0.4.1.dist-info/WHEEL
snaphu-0.4.1.dist-info/METADATA
snaphu-0.4.1.dist-info/licenses/LICENSE-Apache-2.0
snaphu-0.4.1.dist-info/licenses/LICENSE-BSD-3-Clause
snaphu-0.4.1.dist-info/licenses/ext/snaphu/README
snaphu/_conncomp.py
snaphu/snaphu
snaphu/_version.py
snaphu/_check.py
snaphu/__init__.py
snaphu/_unwrap.py
snaphu/.gitignore
snaphu/_util.py
snaphu/py.typed
snaphu/_snaphu.py
snaphu/io/_raster.py
snaphu/io/__init__.pyi
snaphu/io/__init__.py
snaphu/io/_dataset.py
