Metadata-Version: 2.1
Name: snaphu
Version: 0.4.1
Summary: A simple Python wrapper for SNAPHU
Keywords: insar,phase-unwrapping,radar,remote-sensing,sar,synthetic-aperture-radar
Author-Email: Geoffrey Gunter <geoffrey.m.gunter@jpl.nasa.gov>
Classifier: Development Status :: 4 - Beta
Classifier: Intended Audience :: Science/Research
Classifier: License :: Free for non-commercial use
Classifier: License :: OSI Approved :: Apache Software License
Classifier: License :: OSI Approved :: BSD License
Classifier: License :: Other/Proprietary License
Classifier: Operating System :: MacOS
Classifier: Operating System :: POSIX :: Linux
Classifier: Operating System :: Unix
Classifier: Programming Language :: Python
Classifier: Topic :: Scientific/Engineering
Project-URL: Discussions, https://github.com/isce-framework/snaphu-py/discussions
Project-URL: Homepage, https://github.com/isce-framework/snaphu-py
Project-URL: Issues, https://github.com/isce-framework/snaphu-py/issues
Requires-Python: >=3.9
Requires-Dist: numpy>=1.20
Requires-Dist: rasterio>=1.2; extra == "raster"
Requires-Dist: pytest>=6; extra == "test"
Requires-Dist: pytest-cov>=3; extra == "test"
Provides-Extra: raster
Provides-Extra: test
